{
	"stateName":"showDetailOfCPReport.showDetailOfDamageCP",
	"url": "/showDetailOfDamageCP",
	"params": ["cgtShowDetailOfDamageCPIn"],
	"sticky": true,

	"loadModule":["ngMessages", "uiDate", "ngFileUpload", "uiSelect"],
	"loadCommonComponent": ["T3_CCP_UI_Grid.tablas","T3_CCP_UI_Modales","T3_CCP_UI_datePicker.inputDate", null],
	"loadCG":[
		{"name":"showDetailOfDamageCP","tipos":"c,co,s,m"},
         {"name":"manageCPAttachment","tipos":"c,co,d,s,m"},
         {"name":"manageCPContact","tipos":"c,co,d,s,m"}
	]
}